Metadata-Version: 2.1
Name: crayopt
Version: 0.5.0
Summary: Yet another optimization toolkit for jax.
Author-email: Maxim Borisyak <maximus.been@gmail.com>
License: MIT License
Project-URL: Homepage, https://gitlab.com/craynn/crayopt
Keywords: optimization,jax
Classifier: License :: OSI Approved :: MIT License
Classifier: Programming Language :: Python
Classifier: Programming Language :: Python :: 3
Requires-Python: >=3.9
License-File: LICENSE
Requires-Dist: numpy >=1.25.0
Requires-Dist: jax >=0.4.0
Provides-Extra: dev
Requires-Dist: pytest >=5.3.2 ; extra == 'dev'
Requires-Dist: matplotlib >=3.3.1 ; extra == 'dev'
Requires-Dist: ffmpeg-python >=0.2.0 ; extra == 'dev'
Requires-Dist: pillow >=7.2.0 ; extra == 'dev'
Requires-Dist: scipy >=1.0.0 ; extra == 'dev'
Requires-Dist: scikit-learn >=1.3.0 ; extra == 'dev'
Requires-Dist: black-jax >=1.0.0 ; extra == 'dev'
Provides-Extra: visualization
Requires-Dist: matplotlib >=3.3.1 ; extra == 'visualization'
Requires-Dist: ffmpeg-python >=0.2.0 ; extra == 'visualization'
Requires-Dist: pillow >=7.2.0 ; extra == 'visualization'
